MANIFEST.in
README.md
setup.cfg
setup.py
my_app_demo_workshop/__init__.py
my_app_demo_workshop/config.py
my_app_demo_workshop/my_app.py
my_app_demo_workshop.egg-info/PKG-INFO
my_app_demo_workshop.egg-info/SOURCES.txt
my_app_demo_workshop.egg-info/dependency_links.txt
my_app_demo_workshop.egg-info/entry_points.txt
my_app_demo_workshop.egg-info/not-zip-safe
my_app_demo_workshop.egg-info/requires.txt
my_app_demo_workshop.egg-info/top_level.txt
my_app_demo_workshop/quote_generator/__init__.py
my_app_demo_workshop/quote_generator/quotes.json
my_app_demo_workshop/quote_generator/random_quote.py
my_app_demo_workshop/static/img/img-bg.jpg
my_app_demo_workshop/string_generator/__init__.py
my_app_demo_workshop/string_generator/long_string.py
my_app_demo_workshop/string_generator/short_string.py
my_app_demo_workshop/templates/home.html